airflow/providers/clickhouse/__init__.py
airflow/providers/clickhouse/get_provider_info.py
airflow/providers/clickhouse/hooks/__init__.py
airflow/providers/clickhouse/hooks/clickhouse.py
airflow/providers/clickhouse/operators/__init__.py
airflow/providers/clickhouse/operators/clickhouse.py
airflow/providers/clickhouse/sensors/__init__.py
airflow/providers/clickhouse/sensors/clickhouse.py
airflow_clickhouse_connect-0.2.5.dist-info/LICENSE
airflow_clickhouse_connect-0.2.5.dist-info/METADATA
airflow_clickhouse_connect-0.2.5.dist-info/WHEEL
airflow_clickhouse_connect-0.2.5.dist-info/entry_points.txt
airflow_clickhouse_connect-0.2.5.dist-info/top_level.txt
airflow_clickhouse_connect-0.2.5.dist-info/RECORD
