Metadata-Version: 2.1
Name: airflow-clickhouse-connect
Version: 0.2.5
Summary: Provider for Apache Airflow. Implements airflow-clickhouse-connect package
Home-page: https://github.com/amirtaherkhani
Download-URL: https://pypi.org/project/airflow-clickhouse-connect/#files
Author: Amir Taherkhani
Author-email: amirtaherkhani@outlook.com
License: Apache License 2.0
Project-URL: Documentation, https://github.com/amirtaherkhani/airflow-clickhouse-connect
Project-URL: Bug Tracker, https://github.com/amirtaherkhani/airflow-clickhouse-connect/issues
Project-URL: Source Code, https://github.com/amirtaherkhani/airflow-clickhouse-connect
Classifier: Development Status :: 5 - Production/Stable
Classifier: Environment :: Console
Classifier: Environment :: Web Environment
Classifier: Intended Audience :: Developers
Classifier: Intended Audience :: System Administrators
Classifier: Framework :: Apache Airflow
Classifier: Framework :: Apache Airflow :: Provider
Classifier: License :: OSI Approved :: Apache Software License
Classifier: Programming Language :: Python :: 3.8
Classifier: Programming Language :: Python :: 3.9
Classifier: Programming Language :: Python :: 3.10
Classifier: Topic :: System :: Monitoring
Requires-Python: ~=3.8
License-File: LICENSE
Requires-Dist: apache-airflow (>=2.5.0)
Requires-Dist: clickhouse-driver (>=0.2.5)
Requires-Dist: apache-airflow-providers-mysql (>=4.0.2)
Requires-Dist: pandas (>=1.5)
Requires-Dist: lxml (>=4.9.2)
Requires-Dist: numexpr (>=2.6.1)
Requires-Dist: clickhouse-connect (>=0.5.20)
